ambsql/__init__.py
ambsql/ambsql.py
ambsql-1.1.5.dist-info/LICENSE
ambsql-1.1.5.dist-info/METADATA
ambsql-1.1.5.dist-info/WHEEL
ambsql-1.1.5.dist-info/top_level.txt
ambsql-1.1.5.dist-info/RECORD
