Metadata-Version: 2.1
Name: ambsql
Version: 1.1.5
Summary: AmbSQL is a DBMS which is approx 10x faster and the most EASY to operate on.
Home-page: https://github.com/ambujraj/AmbSQL
Author: Ambuj Raj
Author-email: thecoderguy@outlook.com
License: UNKNOWN
Keywords: database management system python ambsql terminal command-line
Platform: any
Classifier: Programming Language :: Python :: 3
Classifier: License :: OSI Approved :: MIT License
Classifier: Operating System :: OS Independent
